kryptoon/__init__.py
kryptoon/__init__.pyi
kryptoon/__internal__.cpython-313-x86_64-linux-gnu.so
kryptoon/classic/__init__.py
kryptoon/classic/__init__.pyi
kryptoon/classic/encode/__init__.py
kryptoon/classic/encode/__init__.pyi
kryptoon/classic/encode/__internal__.py
kryptoon/classic/encode/__internal__.pyi
kryptoon/classic/hash/__init__.py
kryptoon/classic/hash/__init__.pyi
kryptoon/classic/hash/__internal__.py
kryptoon/classic/hash/__internal__.pyi
kryptoon/classic/phf/__init__.py
kryptoon/classic/phf/__init__.pyi
kryptoon/classic/phf/__internal__.py
kryptoon/classic/phf/__internal__.pyi
kryptoon/quantum/__init__.py
kryptoon/quantum/__init__.pyi
kryptoon/quantum/dsa/__init__.py
kryptoon/quantum/dsa/__init__.pyi
kryptoon/quantum/dsa/__internal__.py
kryptoon/quantum/dsa/__internal__.pyi
kryptoon/quantum/kem/__init__.py
kryptoon/quantum/kem/__init__.pyi
kryptoon/quantum/kem/__internal__.py
kryptoon/quantum/kem/__internal__.pyi
kryptoon/typing/__init__.py
kryptoon/typing/__init__.pyi
kryptoon-2026.1.31.dist-info/METADATA
kryptoon-2026.1.31.dist-info/WHEEL
kryptoon-2026.1.31.dist-info/RECORD
