Metadata-Version: 2.4
Name: kryptoon
Version: 2026.1.31
Classifier: Programming Language :: Python :: Implementation :: CPython
Classifier: Programming Language :: Python :: Implementation :: PyPy
Classifier: Programming Language :: Rust
Summary: Python Cryptography
Keywords: python,cryptography
Home-Page: https://github.com/bitmolester/kryptoon
Author-email: Anonymous <me@pishvaveisi.com>
License: Unlicense
Project-URL: Homepage, https://github.com/bitmolester/kryptoon
Project-URL: Documentation, https://github.com/bitmolester/kryptoon
Project-URL: Source Code, https://github.com/bitmolester/kryptoon
